[
  {
    "description": "  Как разработчик\n  Я хочу убедиться что BDD тесты работают\n  Чтобы использовать их для автоматизации",
    "elements": [
      {
        "description": "",
        "id": "базовая-проверка-работы-bdd-тестов;простая-проверка-загрузки-сайта",
        "keyword": "Сценарий",
        "line": 8,
        "name": "Простая проверка загрузки сайта",
        "steps": [
          {
            "keyword": "Before",
            "hidden": true,
            "result": {
              "status": "passed",
              "duration": 631926750
            }
          },
          {
            "arguments": [],
            "keyword": "Дано ",
            "line": 9,
            "name": "что сайт автосалона \"Cool Cars Amsterdam\" доступен",
            "match": {
              "location": "file:/Users/andreymaznyak/projects/car-project/landings/car-dealer-demo/features/step-definitions/navigation.js:5"
            },
            "result": {
              "status": "passed",
              "duration": 311542
            }
          },
          {
            "arguments": [],
            "keyword": "И ",
            "line": 10,
            "name": "development сервер запущен на \"http://localhost:5173\"",
            "match": {
              "location": "file:/Users/andreymaznyak/projects/car-project/landings/car-dealer-demo/features/step-definitions/navigation.js:9"
            },
            "result": {
              "status": "passed",
              "duration": 69000
            }
          },
          {
            "arguments": [],
            "keyword": "Когда ",
            "line": 11,
            "name": "я открываю главную страницу",
            "match": {
              "location": "file:/Users/andreymaznyak/projects/car-project/landings/car-dealer-demo/features/step-definitions/navigation.js:20"
            },
            "result": {
              "status": "passed",
              "duration": 1664718750
            }
          },
          {
            "arguments": [],
            "keyword": "Тогда ",
            "line": 12,
            "name": "я вижу заголовок страницы \"Cool Cars - Premium Used Cars in Amsterdam\"",
            "match": {
              "location": "file:/Users/andreymaznyak/projects/car-project/landings/car-dealer-demo/features/step-definitions/navigation.js:38"
            },
            "result": {
              "status": "passed",
              "duration": 14076916
            }
          },
          {
            "keyword": "After",
            "hidden": true,
            "result": {
              "status": "passed",
              "duration": 18823582
            }
          }
        ],
        "tags": [],
        "type": "scenario"
      }
    ],
    "id": "базовая-проверка-работы-bdd-тестов",
    "line": 2,
    "keyword": "Функция",
    "name": "Базовая проверка работы BDD тестов",
    "tags": [],
    "uri": "features/basic-test.feature"
  }
]